netblocks3/LICENSE
netblocks3/README.md
netblocks3/__init__.py
netblocks3/netblocks.py
netblocks3-0.0.15.dist-info/LICENSE
netblocks3-0.0.15.dist-info/WHEEL
netblocks3-0.0.15.dist-info/METADATA
netblocks3-0.0.15.dist-info/RECORD
