Metadata-Version: 2.1
Name: netblocks3
Version: 0.0.15
Summary: Get the Cloud Provider netblocks (Python3 version)
License: Apache-2.0
Author: hm-distro
Requires-Python: >=3.6,<4.0
Classifier: License :: OSI Approved :: Apache Software License
Classifier: Programming Language :: Python :: 3
Classifier: Programming Language :: Python :: 3.6
Classifier: Programming Language :: Python :: 3.7
Classifier: Programming Language :: Python :: 3.8
Requires-Dist: requests (>=2.23.0,<3.0.0)
Project-URL: Github, https://github.com/tomasfse/netblocks
